{
    "entities": [
        {
            "type": "player",
            "x": 1,
            "y": 2
        },
        {
            "type": "door",
            "x": 2,
            "y": 3,
            "key": 2
        },
        {
            "type": "arrow",
            "x": 1,
            "y": 1
        },
        {
            "type": "arrow",
            "x": 2,
            "y": 1
        },
        {
            "type": "key",
            "x": 3,
            "y": 1,
            "key": 1
        },
        {
            "type": "sword",
            "x": 3,
            "y": 7
        },
        {
            "type": "sun_stone",
            "x": 4,
            "y": 1
        },
        {
            "type": "exit",
            "x": 8,
            "y": 8
        },
        {
            "type": "mercenary",
            "x": 24,
            "y": 6
        }
    ],
    "goal-condition": {
        "goal": "exit"
    }
}